drb/topics/sentinel5p/__init__.py
drb/topics/sentinel5p/_version.py
drb/topics/sentinel5p/cortex.yml
drb/topics/sentinel5p/auxiliary/__init__.py
drb/topics/sentinel5p/auxiliary/cortex.yml
drb/topics/sentinel5p/level1/__init__.py
drb/topics/sentinel5p/level1/cortex.yml
drb/topics/sentinel5p/level2/__init__.py
drb/topics/sentinel5p/level2/cortex.yml
drb_topic_sentinel5p-1.3.0.data/data/requirements.txt
drb_topic_sentinel5p-1.3.0.dist-info/LICENCE.txt
drb_topic_sentinel5p-1.3.0.dist-info/METADATA
drb_topic_sentinel5p-1.3.0.dist-info/WHEEL
drb_topic_sentinel5p-1.3.0.dist-info/entry_points.txt
drb_topic_sentinel5p-1.3.0.dist-info/top_level.txt
drb_topic_sentinel5p-1.3.0.dist-info/RECORD
