Metadata-Version: 2.1
Name: drb-topic-sentinel5p
Version: 1.3.0
Summary: sentinel-5P topic for DRB Python
Home-page: https://gitlab.com/drb-python/topics/sentinel5p
Author: GAEL Systems
Author-email: drb-python@gael.fr
License: UNKNOWN
Platform: UNKNOWN
Classifier: Programming Language :: Python :: 3.8
Classifier: License :: OSI Approved :: GNU Lesser General Public License v3 (LGPLv3)
Classifier: Programming Language :: Python :: 3.8
Requires-Python: >=3.8
License-File: LICENCE.txt
Requires-Dist: drb ~=2.2.0
Requires-Dist: drb-driver-netcdf ~=1.3.0
